mcp_facebook_ads/__init__.py
mcp_facebook_ads/__main__.py
mcp_facebook_ads/server.py
mcp_facebook_ads-0.1.0.dist-info/METADATA
mcp_facebook_ads-0.1.0.dist-info/WHEEL
mcp_facebook_ads-0.1.0.dist-info/entry_points.txt
mcp_facebook_ads-0.1.0.dist-info/licenses/LICENSE
mcp_facebook_ads-0.1.0.dist-info/RECORD
