Metadata-Version: 2.4
Name: mcp_facebook_ads
Version: 0.1.0
Summary: MCP server em Python para consultar dados da Facebook Ads Marketing API
Project-URL: Homepage, https://github.com/marcelo/mcp-facebook-ads
Author: Marcelo
License: MIT License
License-File: LICENSE
Requires-Python: >=3.10
Requires-Dist: mcp>=1.6.0
Requires-Dist: python-dotenv>=1.0.0
Requires-Dist: requests>=2.32.0
